{
  "course": "SS1 Financial Accounting",
  "term": "Third Term",
  "week": 10,
  "topic": "Revisit Adjustments: Bad Debts, Discounts, Prepayments & Accruals",
  "subUnits": [
    {
      "id": "ss1_fa_t3_w10_su1",
      "title": "10.1 Revisiting Adjustments: Bad Debts, Provision for Bad Debts, Discounts, Prepayments & Accruals",
      "notes": [
        "Revisiting Adjustments in Final Accounts",
        "",
        "Key Concepts:",
        "1. Bad Debts and Provision for Bad Debts:",
        "   a) Bad Debts:",
        "      - Actual debts that cannot be recovered from customers",
        "      - Treated as expense in Profit and Loss Account",
        "      - Journal Entry: Debit Bad Debts Expense, Credit Debtors Account",
        "",
        "   b) Provision for Bad Debts:",
        "      - Estimated amount set aside for future bad debts",
        "      - Calculated as percentage of debtors (e.g., 5% of debtors)",
        "      - Treated as expense in Profit and Loss Account",
        "      - Shown as deduction from debtors in Balance Sheet",
        "",
        "2. Discount Allowed and Discount Received:",
        "   a) Discount Allowed:",
        "      - Deduction given to customers for early payment",
        "      - Treated as expense in Profit and Loss Account",
        "      - Shown as deduction from debtors in Balance Sheet",
        "",
        "   b) Discount Received:",
        "      - Deduction received from suppliers for early payment",
        "      - Treated as income in Profit and Loss Account",
        "      - Shown as deduction from creditors in Balance Sheet",
        "",
        "3. Prepayments and Accruals:",
        "   a) Prepayments (Prepaid Expenses):",
        "      - Expenses paid in advance for future periods",
        "      - Treated as current asset in Balance Sheet",
        "      - Deducted from expense in Profit and Loss Account",
        "",
        "   b) Accruals (Outstanding Expenses):",
        "      - Expenses incurred but not yet paid",
        "      - Treated as current liability in Balance Sheet",
        "      - Added to expense in Profit and Loss Account",
        "",
        "4. Posting Adjustments to Ledger and Final Accounts:",
        "   - Bad Debts: Debit Bad Debts Expense, Credit Debtors",
        "   - Provision for Bad Debts: Debit P&L, Credit Provision Account",
        "   - Discount Allowed: Debit Discount Allowed, Credit Debtors",
        "   - Discount Received: Debit Creditors, Credit Discount Received",
        "   - Prepayments: Debit Prepaid Expense (Asset), Credit Expense",
        "   - Accruals: Debit Expense, Credit Accrued Expense (Liability)",
        "",
        "5. Comprehensive Adjustment Process:",
        "   - Identify adjustments from trial balance and additional information",
        "   - Post adjusting entries to ledger accounts",
        "   - Prepare adjusted trial balance",
        "   - Prepare final accounts with all adjustments",
        "",
        "Nigerian Context:",
        "   - Nigerian businesses face bad debts from credit sales in volatile markets",
        "   - Provision for bad debts is essential for prudent financial reporting (FIRS compliance)",
        "   - Prepayments common in Nigerian rent, insurance, and subscription payments",
        "   - Accruals frequent in utility bills, salaries, and supplier payments",
        "   - Discounts widely used in Nigerian wholesale and retail trade for prompt payment",
        "",
        "Practical Activities:",
        "   - Teacher demonstrates preparation of Trading and P&L Account with multiple adjustments",
        "   - Students practice calculating bad debts, provision for bad debts, and discounts",
        "   - Students post prepayments and accruals to ledger and final accounts",
        "",
        "Common Misconceptions:",
        "   - 'Bad debts and provision for bad debts are the same': Bad debts are actual losses; provision is estimated future loss",
        "   - 'Discount allowed increases profit': Discount allowed reduces profit as it is an expense",
        "   - 'Prepayments increase expenses': Prepayments reduce current period expenses",
        "",
        "Conclusion:",
        "   - Adjustments ensure expenses and incomes are matched to correct accounting period",
        "   - Bad debts, provision, discounts, prepayments, and accruals affect final accounts",
        "   - Proper posting ensures accurate financial reporting and regulatory compliance",
        "   - Mastery supports professional accounting and audit readiness"
      ],
      "diagramDescriptions": [
        "Chart of adjustment types and their treatment in final accounts",
        "Diagram of ledger postings for bad debts, discounts, prepayments, and accruals",
        "Sample final accounts with multiple adjustments",
        "Nigerian context: Credit sales, utility bills, and rent prepayments",
        "Common misconceptions and clarifications"
      ],
      "videoId": "",
      "youtubeQuery": "SS1 Financial Accounting adjustments bad debts discounts prepayments accruals site:youtube.com",
      "quiz": [
        {"q": "Bad debts are treated as:", "opts": ["Asset", "Liability", "Expense", "Income"], "ans": 2, "explanation": "Bad debts are unrecoverable amounts from debtors, treated as an expense in Profit and Loss Account."},
        {"q": "Provision for bad debts is calculated as:", "opts": ["Percentage of sales", "Percentage of debtors", "Percentage of creditors", "Percentage of capital"], "ans": 1, "explanation": "Provision for bad debts is typically a percentage of total debtors to cover future losses."},
        {"q": "Discount allowed to debtors is recorded as:", "opts": ["Income", "Expense", "Asset", "Liability"], "ans": 1, "explanation": "Discount allowed is a deduction given to customers, treated as an expense in Profit and Loss Account."},
        {"q": "Prepayments in the Balance Sheet are shown as:", "opts": ["Current liability", "Current asset", "Fixed asset", "Long-term liability"], "ans": 1, "explanation": "Prepayments represent expenses paid in advance, classified as current assets."},
        {"q": "Accruals in the Profit and Loss Account are:", "opts": ["Deducted from expenses", "Added to expenses", "Ignored", "Transferred to capital"], "ans": 1, "explanation": "Accruals (outstanding expenses) are added to expenses to match costs to the correct period."},
        {"q": "In Nigerian context, bad debts commonly arise from:", "opts": ["Cash sales", "Credit sales to unreliable customers", "Bank loans", "Owner's drawings"], "ans": 1, "explanation": "Credit sales in volatile Nigerian markets often lead to unrecoverable debts."},
        {"q": "A common misconception about provision for bad debts is:", "opts": ["It is an estimate of future losses", "It is the same as actual bad debts", "It is shown as deduction from debtors", "It is charged to Profit and Loss Account"], "ans": 1, "explanation": "Provision for bad debts is an estimated future loss, not actual bad debts incurred."},
        {"q": "When recording a prepayment, you should:", "opts": ["Debit expense, credit cash", "Debit prepaid expense (asset), credit expense", "Debit cash, credit expense", "Ignore the prepayment"], "ans": 1, "explanation": "Prepayments are recorded by debiting prepaid expense (asset) and crediting the expense account."},
        {"q": "Discount received from creditors is treated as:", "opts": ["Expense", "Income", "Asset", "Liability"], "ans": 1, "explanation": "Discount received is a deduction from amounts owed to creditors, treated as income in Profit and Loss Account."},
        {"q": "To ensure accurate final accounts, you should:", "opts": ["Ignore adjustments", "Post all adjustments to ledger and final accounts", "Only adjust cash transactions", "Skip provision for bad debts"], "ans": 1, "explanation": "All adjustments must be posted to ledger and final accounts to ensure accurate financial reporting."}
      ]
    }
  ]
}