{
  "course": "SSS3 Geography",
  "term": "First Term",
  "week": 3,
  "topic": "Karst (Limestone) Topography",
  "subUnits": [
    {
      "id": "sss3_geo_t1_w3_su1",
      "title": "3.1 Meaning and Characteristics of Karst Topography",
      "notes": [
        "Karst Topography:",
        "• A distinctive landscape formed by the dissolution of soluble rocks, primarily limestone, dolomite, and gypsum",
        "• Named after the Karst region in Slovenia (formerly part of Yugoslavia)",
        "• Characterized by underground drainage, sinkholes, caves, and rugged surface features",
        "Conditions Necessary for Karst Development:",
        "1. Soluble Rock:",
        "   • Limestone (calcium carbonate, CaCO₃) is most common",
        "   • Dolomite (calcium magnesium carbonate) and gypsum also form karst",
        "   • Rock must be thick, pure, and well-jointed to allow water penetration",
        "2. Climate:",
        "   • Adequate rainfall to provide water for dissolution",
        "   • Warm temperatures accelerate chemical weathering",
        "   • Tropical and temperate humid climates favor karst development",
        "3. Vegetation Cover:",
        "   • Dense vegetation produces organic acids that enhance dissolution",
        "   • Root action opens joints and fractures for water infiltration",
        "4. Time:",
        "   • Karst features develop over thousands to millions of years",
        "   • Older landscapes show more advanced karst features",
        "5. Drainage:",
        "   • Good surface and subsurface drainage allows water to circulate through rock",
        "   • Absence of impermeable layers that would block water flow",
        "Chemical Process of Limestone Dissolution:",
        "• Carbonation: The key chemical reaction in karst formation",
        "  CO₂ (from air/soil) + H₂O → H₂CO₃ (carbonic acid)",
        "  H₂CO₃ + CaCO₃ (limestone) → Ca(HCO₃)₂ (calcium bicarbonate, soluble)",
        "• Process:",
        "  1. Rainwater absorbs CO₂ from atmosphere and soil → becomes weak carbonic acid",
        "  2. Acidic water percolates through joints and bedding planes in limestone",
        "  3. Carbonic acid dissolves calcium carbonate → forms soluble calcium bicarbonate",
        "  4. Dissolved material is carried away in solution",
        "  5. Over time, this enlarges cracks → forms caves, sinkholes, and other karst features",
        "• Re-precipitation: When calcium bicarbonate solution loses CO₂ (e.g., in caves), calcium carbonate re-deposits as:",
        "  - Stalactites (hang from cave ceiling)",
        "  - Stalagmites (grow up from cave floor)",
        "  - Columns (when stalactite and stalagmite join)",
        "Characteristics of Karst Landscapes:",
        "1. Surface Features:",
        "   • Rugged, irregular topography with few surface streams",
        "   • Abundance of depressions: sinkholes, dolines, uvalas",
        "   • Exposed rock surfaces (limestone pavements) with solution grooves (grikes) and blocks (clints)",
        "   • Dry valleys: Former river valleys now drained underground",
        "2. Subsurface Features:",
        "   • Extensive cave and cavern systems",
        "   • Underground rivers and lakes",
        "   • Vertical shafts (potholes) connecting surface to underground drainage",
        "3. Hydrological Characteristics:",
        "   • Disappearing streams: Surface rivers that vanish into sinkholes",
        "   • Resurgences: Underground rivers re-emerging at surface",
        "   • Lack of surface drainage network; water flows underground",
        "4. Soil and Vegetation:",
        "   • Thin, poor soils due to rapid drainage and dissolution",
        "   • Vegetation often sparse or adapted to rocky, dry conditions",
        "Types of Karst Regions:",
        "1. Tropical Karst:",
        "   • Found in humid tropical regions (Southeast Asia, Caribbean)",
        "   • Features: Tower karst (steep-sided limestone towers), extensive cave systems",
        "   • Example: Guilin (China), Ha Long Bay (Vietnam)",
        "2. Temperate Karst:",
        "   • Found in mid-latitude regions (Europe, North America)",
        "   • Features: Limestone pavements, dolines, cave systems",
        "   • Example: Yorkshire Dales (UK), Mammoth Cave (USA)",
        "3. Glacial Karst:",
        "   • Karst features modified by glacial erosion",
        "   • Features: Glacially sculpted limestone, ice-marginal features",
        "   • Example: Parts of the Alps, Scandinavia",
        "4. Coastal Karst:",
        "   • Karst developed in coastal limestone",
        "   • Features: Sea caves, cliffs, notches, coastal sinkholes",
        "   • Example: Mediterranean coasts, Caribbean islands",
        "Global Distribution of Karst:",
        "• Major karst regions:",
        "  - Europe: Dinaric Alps (Slovenia, Croatia), Yorkshire (UK), France",
        "  - Asia: China (Guilin, Yunnan), Vietnam, Malaysia",
        "  - Americas: Kentucky/Tennessee (USA), Yucatan Peninsula (Mexico), Jamaica",
        "  - Africa: Madagascar, parts of East Africa",
        "  - Oceania: New Zealand, Papua New Guinea",
        "• Nigeria has limited but notable karst features:",
        "  - Limestone areas in Sokoto, Benue, Cross River states",
        "  - Cave systems in Mambilla Plateau, Oban Hills",
        "  - Potential for karst development where limestone is exposed"
      ],
      "diagramDescriptions": [
        "Chemical weathering diagram: carbonation reaction showing CO₂ + H₂O + CaCO₃ → Ca(HCO₃)₂",
        "Karst landscape cross-section: surface features (sinkholes, limestone pavement) and subsurface (caves, underground rivers)",
        "Stalactite and stalagmite formation diagram showing water dripping and mineral deposition",
        "World map highlighting major karst regions with examples labeled",
        "Nigeria map showing limestone areas and potential karst locations"
      ],
      "videoId": "",
      "youtubeQuery": "Karst topography limestone dissolution geography SSS3 site:youtube.com",
      "quiz": [
        {"q": "Karst topography is primarily formed by the dissolution of:", "opts": ["Granite", "Limestone", "Sandstone", "Basalt"], "ans": 1, "explanation": "Karst landscapes develop through chemical dissolution of soluble rocks, primarily limestone (calcium carbonate)."},
        {"q": "The key chemical process in karst formation is:", "opts": ["Oxidation", "Carbonation", "Hydrolysis", "Frost action"], "ans": 1, "explanation": "Carbonation involves carbonic acid (from CO₂ + H₂O) dissolving calcium carbonate in limestone to form soluble calcium bicarbonate."},
        {"q": "A sinkhole (doline) is formed when:", "opts": ["A volcano erupts", "The roof of an underground cavity collapses", "A river erodes a valley", "Wind erodes rock"], "ans": 1, "explanation": "Sinkholes form when dissolution enlarges underground cavities until the surface layer collapses, creating a depression."},
        {"q": "Stalactites are found:", "opts": ["Growing up from cave floors", "Hanging from cave ceilings", "Only in tropical regions", "Only in coastal areas"], "ans": 1, "explanation": "Stalactites form as mineral-rich water drips from cave ceilings, depositing calcium carbonate as it loses CO₂."},
        {"q": "A disappearing stream in karst terrain:", "opts": ["Flows continuously on the surface", "Vanishes into a sinkhole to flow underground", "Only occurs in deserts", "Is always polluted"], "ans": 1, "explanation": "Disappearing streams enter sinkholes or fissures and continue flowing through underground cave systems."},
        {"q": "Limestone pavements are characterized by:", "opts": ["Smooth, flat surfaces only", "Grikes (grooves) and clints (blocks)", "Only found underwater", "Only in cold climates"], "ans": 1, "explanation": "Limestone pavements feature grikes (solution-enlarged joints) separating clints (blocks of limestone), formed by surface dissolution."},
        {"q": "Tropical karst is notable for:", "opts": ["Only small features", "Tower karst and extensive cave systems", "Only coastal features", "Only glacial modifications"], "ans": 1, "explanation": "Tropical karst, with high rainfall and temperatures, develops dramatic tower karst (steep limestone towers) and extensive cave systems."},
        {"q": "Re-precipitation of calcium carbonate in caves forms:", "opts": ["Only stalactites", "Stalactites, stalagmites, and columns", "Only sinkholes", "Only limestone pavements"], "ans": 1, "explanation": "When calcium bicarbonate solution loses CO₂ in caves, calcium carbonate re-deposits as stalactites (ceiling), stalagmites (floor), or columns (joined)."},
        {"q": "Karst landscapes typically have:", "opts": ["Dense surface drainage networks", "Few surface streams and abundant underground drainage", "Only surface rivers", "Only lakes"], "ans": 1, "explanation": "Karst hydrology is dominated by underground drainage; surface streams are rare as water quickly enters the subsurface through joints and sinkholes."},
        {"q": "In Nigeria, karst features are most likely found in areas with:", "opts": ["Only granite rocks", "Exposed limestone deposits", "Only coastal sands", "Only volcanic rocks"], "ans": 1, "explanation": "Karst development requires soluble rock; in Nigeria, limestone areas in Sokoto, Benue, and Cross River states have potential for karst features."}
      ]
    },
    {
      "id": "sss3_geo_t1_w3_su2",
      "title": "3.2 Surface and Underground Features of Karst Regions",
      "notes": [
        "Surface Features of Karst Regions:",
        "1. Sinkholes (Dolines):",
        "   • Definition: Closed depressions in karst terrain, typically circular or oval",
        "   • Formation:",
        "     a) Solution sinkhole: Gradual dissolution of limestone at surface",
        "     b) Collapse sinkhole: Roof of underground cavity collapses",
        "     c) Suffosion sinkhole: Soil washed into underlying cavities",
        "   • Size: Few meters to hundreds of meters in diameter",
        "   • Significance: Common entry points for surface water into underground drainage",
        "   • Hazards: Sudden collapse can damage infrastructure",
        "2. Uvalas:",
        "   • Definition: Compound depressions formed by merging of multiple sinkholes",
        "   • Larger and more irregular than individual dolines",
        "   • Represent advanced stage of karst development",
        "3. Poljes:",
        "   • Definition: Large, flat-floored enclosed depressions with steep sides",
        "   • Size: Kilometers long, hundreds of meters wide",
        "   • Often have seasonal lakes (polje lakes) that flood in wet season",
        "   • Floor may have alluvial soil suitable for agriculture",
        "   • Example: Popovo Polje (Bosnia)",
        "4. Limestone Pavements:",
        "   • Definition: Exposed, flat or gently sloping limestone surfaces",
        "   • Features:",
        "     - Grikes: Solution-enlarged joints (grooves)",
        "     - Clints: Blocks of limestone between grikes",
        "   • Formation: Glacial scouring removes soil, then dissolution enlarges joints",
        "   • Example: Yorkshire Dales (UK), Burren (Ireland)",
        "5. Dry Valleys:",
        "   • Definition: Former river valleys now without surface streams",
        "   • Formation: Underground drainage captures surface rivers, leaving valleys dry",
        "   • Evidence of past surface drainage in otherwise waterless landscape",
        "6. Karst Windows:",
        "   • Definition: Small openings where underground river is visible from surface",
        "   • Formed when cave roof partially collapses",
        "   • Provide access to underground drainage system",
        "Underground Features of Karst Regions:",
        "1. Caves and Caverns:",
        "   • Definition: Natural underground voids large enough for human entry",
        "   • Formation:",
        "     - Water dissolves limestone along joints and bedding planes",
        "     - Enlargement over time creates passages and chambers",
        "     - Water table fluctuations and erosion shape cave morphology",
        "   • Types:",
        "     - Solution caves: Formed primarily by dissolution",
        "     - Sea caves: Formed by wave action in coastal limestone",
        "     - Lava caves: Formed by lava flows (not true karst)",
        "   • Cave decorations (speleothems):",
        "     - Stalactites: Hang from ceiling, form from dripping water",
        "     - Stalagmites: Grow up from floor, form from splashing water",
        "     - Columns: Formed when stalactite and stalagmite join",
        "     - Flowstones: Sheet-like deposits on cave walls/floors",
        "     - Helictites: Twisted, irregular formations defying gravity",
        "2. Underground Rivers and Lakes:",
        "   • Definition: Watercourses flowing through cave systems",
        "   • Characteristics:",
        "     - Often fast-flowing due to steep gradients",
        "     - Can emerge at resurgences to form surface rivers",
        "     - May contain unique blind, colorless aquatic species",
        "   • Example: Puerto Princesa Underground River (Philippines, UNESCO World Heritage)",
        "3. Shafts and Potholes:",
        "   • Definition: Vertical or near-vertical openings connecting surface to underground",
        "   • Formation: Dissolution along vertical joints, collapse of cave roofs",
        "   • Significance: Important for cave exploration and hydrological studies",
        "   • Hazard: Dangerous for unwary hikers; can be deep and narrow",
        "4. Resurgences (Springs):",
        "   • Definition: Points where underground rivers re-emerge at surface",
        "   • Location: Often at base of limestone hills or valley sides",
        "   • Significance: Source of surface rivers in karst regions",
        "   • Example: Fontaine de Vaucluse (France), one of world's largest springs",
        "Importance of Karst Topography:",
        "1. Economic Importance:",
        "   • Tourism: Caves, scenic landscapes attract visitors (e.g., Carlsbad Caverns, USA)",
        "   • Water resources: Underground aquifers store significant freshwater",
        "   • Mining: Limestone quarried for cement, construction, agriculture",
        "   • Agriculture: Polje floors with alluvial soil can be fertile",
        "2. Environmental Importance:",
        "   • Biodiversity: Unique cave ecosystems with specialized species",
        "   • Water regulation: Karst aquifers store and filter water",
        "   • Carbon cycle: Limestone dissolution and precipitation affect atmospheric CO₂",
        "3. Scientific Importance:",
        "   • Paleoclimate records: Cave deposits (speleothems) preserve climate history",
        "   • Hydrological studies: Understanding groundwater flow in soluble rocks",
        "   • Geomorphological research: Landscape evolution in soluble rocks",
        "Challenges and Hazards of Karst Regions:",
        "1. Water Supply Challenges:",
        "   • Rapid infiltration means surface water scarce; reliance on groundwater",
        "   • Groundwater vulnerable to pollution (no natural filtration)",
        "   • Difficult to locate and access underground water sources",
        "2. Engineering and Construction Challenges:",
        "   • Sinkhole collapse risk threatens buildings, roads, pipelines",
        "   • Foundation instability on soluble rock",
        "   • Difficulty in excavating due to caves and voids",
        "3. Environmental Vulnerabilities:",
        "   • Pollution spreads rapidly through underground drainage",
        "   • Fragile cave ecosystems easily damaged by human activity",
        "   • Soil erosion on thin karst soils",
        "4. Hazards:",
        "   • Sudden sinkhole formation",
        "   • Flash flooding in poljes and dry valleys",
        "   • Cave-ins and falls in underground features",
        "Conservation and Management of Karst Regions:",
        "• Sustainable land-use planning to avoid high-risk areas",
        "• Protection of recharge areas to maintain groundwater quality",
        "• Regulation of quarrying and mining to minimize landscape damage",
        "• Cave conservation: Limiting access, preventing vandalism, controlling microclimate",
        "• Public education on karst hydrology and hazards",
        "• Research and monitoring of karst processes and changes",
        "Nigerian Context:",
        "• Limited but notable karst features in Nigeria:",
        "  - Limestone areas: Sokoto Basin, Benue Trough, Cross River State",
        "  - Cave systems: Mambilla Plateau, Oban Hills, Yankari Game Reserve",
        "  - Potential for karst tourism and groundwater resources",
        "• Challenges:",
        "  - Limited research and mapping of Nigerian karst",
        "  - Quarrying of limestone without adequate environmental assessment",
        "  - Groundwater pollution risks in karst aquifers",
        "• Opportunities:",
        "  - Development of eco-tourism around cave systems",
        "  - Sustainable management of karst groundwater for communities",
        "  - Scientific research on tropical karst processes"
      ],
      "diagramDescriptions": [
        "Karst surface features diagram: sinkholes, uvalas, poljes, limestone pavement with grikes/clints",
        "Cave system cross-section: showing stalactites, stalagmites, underground river, shafts, resurgence",
        "Sinkhole formation sequence: initial dissolution → cavity enlargement → collapse",
        "World map of notable karst features with examples labeled",
        "Nigeria map highlighting limestone areas and known cave locations"
      ],
      "videoId": "",
      "youtubeQuery": "Karst surface underground features caves sinkholes geography SSS3 site:youtube.com",
      "quiz": [
        {"q": "A polje is best described as:", "opts": ["A small sinkhole", "A large, flat-floored enclosed depression with steep sides", "Only an underground feature", "Only found in deserts"], "ans": 1, "explanation": "Poljes are large, flat-floored karst depressions, often with seasonal lakes, formed by complex dissolution and tectonic processes."},
        {"q": "Grikes and clints are features of:", "opts": ["Sandstone deserts", "Limestone pavements", "Volcanic plateaus", "Glacial valleys"], "ans": 1, "explanation": "Grikes (solution-enlarged joints) and clints (limestone blocks between grikes) characterize limestone pavements in karst regions."},
        {"q": "Stalagmites form by:", "opts": ["Water dripping from cave ceilings", "Water splashing on cave floors", "Only in tropical caves", "Only from salt water"], "ans": 1, "explanation": "Stalagmites grow upward from cave floors as mineral-rich water splashes and deposits calcium carbonate."},
        {"q": "A resurgence in karst terrain is where:", "opts": ["A river disappears underground", "An underground river re-emerges at the surface", "Only rainwater collects", "Only seawater enters"], "ans": 1, "explanation": "Resurgences (or springs) are points where underground rivers flowing through cave systems return to the surface."},
        {"q": "Dry valleys in karst regions are:", "opts": ["Always dry due to lack of rain", "Former river valleys now drained underground", "Only found in deserts", "Only formed by wind erosion"], "ans": 1, "explanation": "Dry valleys were once occupied by surface rivers that have been captured by underground drainage, leaving the valleys dry."},
        {"q": "A major challenge for water supply in karst regions is:", "opts": ["Too much surface water", "Rapid infiltration making groundwater vulnerable to pollution", "Only saltwater intrusion", "Only seasonal droughts"], "ans": 1, "explanation": "Karst aquifers have rapid water flow through conduits, offering little natural filtration, making groundwater highly vulnerable to contamination."},
        {"q": "Cave decorations like stalactites form through:", "opts": ["Erosion by water", "Re-precipitation of dissolved calcium carbonate", "Only volcanic activity", "Only wind deposition"], "ans": 1, "explanation": "Speleothems form when calcium bicarbonate solution loses CO₂ in caves, causing calcium carbonate to precipitate and accumulate."},
        {"q": "In Nigeria, karst features are most likely associated with:", "opts": ["Granite rocks", "Limestone deposits in Sokoto, Benue, Cross River", "Only coastal sands", "Only volcanic rocks"], "ans": 1, "explanation": "Karst requires soluble rock; Nigeria's limestone areas in Sokoto Basin, Benue Trough, and Cross River State have potential for karst development."},
        {"q": "A hazard specific to karst regions is:", "opts": ["Only earthquakes", "Sudden sinkhole collapse", "Only volcanic eruptions", "Only tsunamis"], "ans": 1, "explanation": "Sinkhole collapse is a distinctive karst hazard, where underground cavities enlarge until the surface layer fails suddenly."},
        {"q": "Conservation of karst regions is important because they:", "opts": ["Have no economic value", "Provide unique ecosystems, water resources, and scientific records", "Are only scenic", "Are always stable"], "ans": 1, "explanation": "Karst regions support unique biodiversity, store vital groundwater, preserve paleoclimate records, and offer tourism potential, requiring careful management."}
      ]
    }
  ]
}