{
  "course": "SS2 Physics",
  "term": "Third Term",
  "week": 3,
  "topic": "Electric Field: Coulomb's Law and Electric Field Concepts",
  "subUnits": [
    {
      "id": "ss2_phy_t3_w3_su1",
      "title": "3.1 Coulomb's Law, Electric Field Intensity, and Electric Potential",
      "notes": [
        "Coulomb's Law and Electric Field Concepts",
        "",
        "Key Concepts:",
        "1. Coulomb's Law:",
        "   - Force between two point charges is proportional to product of charges and inversely proportional to square of distance",
        "   - Formula: F = k(q1q2)/r², where k = 1/(4πε₀) ≈ 9×10⁹ N·m²/C²",
        "   - Force is attractive for opposite charges, repulsive for like charges",
        "",
        "2. Electric Field:",
        "   - Region around a charge where electric force is experienced",
        "   - Electric field intensity (E): Force per unit positive charge",
        "   - Formula: E = F/q = kQ/r² (for point charge)",
        "   - Unit: N/C or V/m",
        "",
        "3. Electric Potential:",
        "   - Work done per unit charge to bring a test charge from infinity to a point",
        "   - Formula: V = kQ/r (for point charge)",
        "   - Unit: Volt (V) = J/C",
        "",
        "4. Relationship Between E and V:",
        "   - E = -dV/dr (field is negative gradient of potential)",
        "   - Uniform field: E = V/d (between parallel plates)",
        "",
        "5. Comparison with Gravitational Force:",
        "   - Both follow inverse-square law",
        "   - Electric force is much stronger (≈10³⁶ times for protons)",
        "   - Electric force can be attractive or repulsive; gravity is always attractive",
        "",
        "6. Applications in Nigeria:",
        "   - Lightning protection systems using electric field principles",
        "   - Electrostatic precipitators in Nigerian industries for air pollution control",
        "   - Photocopiers and laser printers using electrostatic principles",
        "",
        "Nigerian Context:",
        "   - Lightning strikes on Nigerian buildings and trees during rainy season",
        "   - Industrial applications in cement factories and power plants",
        "   - School laboratory demonstrations of electric fields with charged rods",
        "",
        "Conclusion:",
        "   - Coulomb's Law quantifies electric force between charges",
        "   - Electric field intensity and potential describe field properties",
        "   - E and V are related by gradient relationship",
        "   - Applications include lightning protection and industrial processes",
        "   - Mastery supports electromagnetism and electrical engineering"
      ],
      "diagramDescriptions": [
        "Chart of Coulomb's Law formula and electric field concepts",
        "Diagram of electric field lines for point charges and parallel plates",
        "Sample calculations for force, field, and potential",
        "Nigerian context: Lightning protection and industrial applications",
        "Common misconceptions and how to avoid them"
      ],
      "videoId": "",
      "youtubeQuery": "SS2 Physics Coulomb's law electric field potential site:youtube.com",
      "quiz": [
        {"q": "Coulomb's Law states that force between charges is:", "opts": ["Proportional to distance", "Proportional to product of charges and inversely proportional to square of distance", "Independent of charge magnitude", "Always attractive"], "ans": 1, "explanation": "Coulomb's Law: F = k(q1q2)/r², force ∝ product of charges and ∝ 1/r²."},
        {"q": "Electric field intensity (E) is defined as:", "opts": ["Force per unit mass", "Force per unit positive charge", "Work per unit charge", "Charge per unit area"], "ans": 1, "explanation": "Electric field intensity E = F/q, force experienced per unit positive test charge."},
        {"q": "The unit of electric potential is:", "opts": ["Newton", "Joule", "Volt", "Coulomb"], "ans": 2, "explanation": "Electric potential is measured in Volts (V), where 1 V = 1 J/C."},
        {"q": "For a point charge, electric field varies with distance as:", "opts": ["E ∝ r", "E ∝ 1/r", "E ∝ 1/r²", "E ∝ r²"], "ans": 2, "explanation": "Electric field due to point charge: E = kQ/r², so E ∝ 1/r²."},
        {"q": "In Nigerian context, electric field principles apply to:", "opts": ["Only cooking", "Lightning protection and industrial precipitators", "Only farming", "Only astronomy"], "ans": 1, "explanation": "Electric field principles are used in lightning protection systems and electrostatic precipitators in Nigeria."},
        {"q": "The force between two like charges is:", "opts": ["Attractive", "Repulsive", "Zero", "Depends on medium only"], "ans": 1, "explanation": "Like charges repel each other according to Coulomb's Law."},
        {"q": "A common misconception about electric fields is:", "opts": ["Field lines start on positive charges", "Field is zero inside a conductor", "Field strength is constant everywhere", "Potential is zero at infinity"], "ans": 2, "explanation": "Electric field strength varies with position; it is not constant everywhere."},
        {"q": "The relationship between E and V is:", "opts": ["E = V × r", "E = -dV/dr", "E = V/r²", "E = V + r"], "ans": 1, "explanation": "Electric field is the negative gradient of electric potential: E = -dV/dr."},
        {"q": "To calculate force between two charges, you should:", "opts": ["Use F = qE only", "Use Coulomb's Law F = k(q1q2)/r²", "Ignore distance", "Assume force is always attractive"], "ans": 1, "explanation": "Coulomb's Law F = k(q1q2)/r² calculates force between point charges."},
        {"q": "Electric potential at a point is:", "opts": ["Force experienced by a charge", "Work done to bring unit charge from infinity", "Field strength at that point", "Charge density"], "ans": 1, "explanation": "Electric potential is work done per unit charge to bring a test charge from infinity to that point."}
      ]
    }
  ]
}