{
  "course": "SS2 Commerce",
  "term": "First Term",
  "week": 4,
  "topic": "Communications",
  "subUnits": [
    {
      "id": "ss2_com_t1_w4_su1",
      "title": "4.1 Internet, Social Media, and E-mail in Business",
      "notes": [
        "Internet, Social Media, and E-mail in Business",
        "",
        "Key Concepts:",
        "1. The Internet:",
        "   a) Meaning:",
        "      - A global network of interconnected computers that communicate using standardized protocols",
        "   b) Business Applications:",
        "      - Research, e-commerce, digital marketing, cloud computing, and remote work",
        "   c) Popular Platforms:",
        "      - YouTube (video sharing and marketing), Facebook and X/Twitter (social networking and brand engagement)",
        "",
        "2. Electronic Mail (E-mail):",
        "   a) Meaning:",
        "      - A method of exchanging digital messages between people using digital devices",
        "   b) Features:",
        "      - Fast, cost-effective, supports attachments (documents, images), and provides a written record",
        "   c) Basic Operations:",
        "      - Opening an account: Registering with a provider (e.g., Gmail, Yahoo) with a unique username and password",
        "      - Sending documents: Composing a message, attaching files, and clicking 'Send'",
        "      - Receiving documents: Checking the inbox, downloading attachments, and replying",
        "",
        "3. Advantages of E-mail and Internet in Commerce:",
        "   - Speed: Instantaneous communication across the globe",
        "   - Cost-effective: Eliminates postage and long-distance call charges",
        "   - Environmental friendliness: Reduces paper usage (paperless office)",
        "   - Accessibility: Can be accessed anytime, anywhere with an internet connection",
        "",
        "4. Disadvantages and Risks:",
        "   - Cybersecurity threats: Phishing, viruses, and hacking",
        "   - Information overload: Too many emails can reduce productivity",
        "   - Dependence on infrastructure: Requires stable electricity and internet connectivity",
        "",
        "5. Netiquette (Internet Etiquette) in Business:",
        "   - Use professional language and clear subject lines",
        "   - Avoid using ALL CAPS (interpreted as shouting)",
        "   - Verify attachments before sending",
        "   - Respect privacy and confidentiality of business information",
        "",
        "Nigerian Context:",
        "   - E-mail is the standard for formal business communication, job applications, and B2B transactions in Nigeria",
        "   - Social media (Instagram, Facebook, X) is heavily used by Nigerian SMEs for digital marketing and sales",
        "   - Challenges: Erratic power supply and internet data costs can hinder seamless digital communication",
        "   - Regulatory framework: NITDA (National Information Technology Development Agency) guides data protection and cybersecurity",
        "",
        "Practical Activities:",
        "   - Teacher demonstrates how to create an e-mail account and send an email with an attachment",
        "   - Students practice drafting professional business emails (e.g., inquiry, quotation)",
        "   - Students discuss the impact of social media on small business growth in Nigeria",
        "",
        "Common Misconceptions:",
        "   - 'E-mail is only for personal use': E-mail is the primary formal communication tool in the corporate world",
        "   - 'Social media is only for entertainment': Platforms like LinkedIn and Instagram are powerful business and marketing tools",
        "   - 'Sending an email guarantees it will be read': Emails can go to spam or be ignored; follow-up is often necessary",
        "",
        "Conclusion:",
        "   - The internet, social media, and e-mail are indispensable tools for modern business communication",
        "   - E-mail provides a fast, formal, and documented method for exchanging business documents",
        "   - Understanding digital etiquette and cybersecurity is crucial for professional success",
        "   - Mastery supports digital literacy, effective business communication, and modern trade practices"
      ],
      "diagramDescriptions": [
        "Chart of internet and social media applications in business",
        "Diagram of the e-mail sending and receiving process",
        "Sample professional business email format",
        "Nigerian context: SME digital marketing, NITDA guidelines, business communication",
        "Common misconceptions and clarifications"
      ],
      "videoId": "",
      "youtubeQuery": "SS2 Commerce internet social media email business communication site:youtube.com",
      "quiz": [
        {"q": "The internet is best described as:", "opts": ["A single computer", "A global network of interconnected computers", "A type of software", "A social media platform"], "ans": 1, "explanation": "The internet is a worldwide system of interconnected computer networks that communicate using standardized protocols."},
        {"q": "A primary advantage of e-mail in business is that it:", "opts": ["Is slower than traditional mail", "Provides a written record and supports attachments", "Requires physical postage", "Cannot be used for formal communication"], "ans": 1, "explanation": "E-mail is fast, cost-effective, provides a digital record, and allows file attachments."},
        {"q": "To send a document via e-mail, you must:", "opts": ["Write it on paper and scan it later", "Use the 'Attach' or 'Attachment' feature before sending", "Call the recipient first", "Print the document"], "ans": 1, "explanation": "The 'Attach' feature allows users to include digital files (documents, images) in an e-mail."},
        {"q": "Which of the following is a common cybersecurity risk associated with e-mail?", "opts": ["Paper cuts", "Phishing and viruses", "Slow internet speed", "High postage costs"], "ans": 1, "explanation": "Phishing, malware, and viruses are significant cybersecurity risks associated with opening suspicious emails or attachments."},
        {"q": "In the Nigerian business context, e-mail is primarily used for:", "opts": ["Informal chatting with friends", "Formal communication, job applications, and B2B transactions", "Playing games", "Watching movies"], "ans": 1, "explanation": "E-mail remains the standard for formal, professional, and documented business communication in Nigeria."},
        {"q": "A key rule of 'Netiquette' (business email etiquette) is to:", "opts": ["Use ALL CAPS to emphasize points", "Use a clear subject line and professional language", "Send emails to everyone in the company", "Ignore attachments"], "ans": 1, "explanation": "Professional email etiquette requires clear subject lines, polite language, and appropriate formatting."},
        {"q": "Social media platforms like Instagram and Facebook are used in commerce for:", "opts": ["Only personal photo sharing", "Digital marketing, customer engagement, and sales", "Writing long academic papers", "Manufacturing goods"], "ans": 1, "explanation": "SMEs and large corporations use social media extensively for marketing, brand building, and direct sales."},
        {"q": "A disadvantage of relying heavily on internet communication is:", "opts": ["It is too slow", "Dependence on stable electricity and internet connectivity", "It uses too much paper", "It cannot send documents"], "ans": 1, "explanation": "Digital communication requires reliable infrastructure (power and internet), which can be a challenge in some areas."},
        {"q": "When opening a new e-mail account, you are typically required to create:", "opts": ["A physical address", "A unique username and password", "A bank account", "A phone number only"], "ans": 1, "explanation": "Creating an email account requires choosing a unique username (email address) and a secure password."},
        {"q": "A common misconception about social media in business is:", "opts": ["It can be used for marketing", "It is only for entertainment and has no business value", "It helps in customer engagement", "It can drive sales"], "ans": 1, "explanation": "Social media is a powerful business tool for marketing, customer service, and brand awareness, not just entertainment."}
      ]
    }
  ]
}