{
  "course": "SS2 Financial Accounting",
  "term": "Third Term",
  "week": 10,
  "topic": "Company Account (Final Account): Balance Sheet Preparation and Analysis",
  "subUnits": [
    {
      "id": "ss2_fa_t3_w10_su1",
      "title": "10.1 Company Balance Sheet: Layout, Preparation, and Interpretation",
      "notes": [
        "Company Balance Sheet: Layout, Preparation, and Interpretation",
        "",
        "Key Concepts:",
        "1. Meaning of Company Balance Sheet:",
        "   - Statement of financial position showing assets, liabilities, and equity at a specific date",
        "   - Prepared after Profit and Loss Appropriation Account",
        "   - Based on accounting equation: Assets = Liabilities + Shareholders' Equity",
        "",
        "2. Layout/Format of Company Balance Sheet:",
        "   a) Vertical Format (Modern):",
        "      - Assets listed first (Fixed Assets, Current Assets)",
        "      - Liabilities and Equity listed below (Non-current Liabilities, Current Liabilities, Shareholders' Equity)",
        "      - Widely used in Nigerian corporate reporting and NSE filings",
        "",
        "   b) T-Shape Format (Conventional):",
        "      - Assets on left side, Liabilities and Equity on right side",
        "      - Traditional format, less common in modern reporting",
        "",
        "3. Classification of Items in Balance Sheet:",
        "   a) Fixed/Non-Current Assets:",
        "      - Land, buildings, plant and machinery, vehicles, intangible assets (goodwill, patents)",
        "      - Shown at net book value (cost less accumulated depreciation)",
        "",
        "   b) Current Assets:",
        "      - Stock, debtors, cash, bank, prepayments, short-term investments",
        "      - Expected to be converted to cash within one year",
        "",
        "   c) Non-Current/Long-Term Liabilities:",
        "      - Debentures, long-term loans, mortgages",
        "      - Due for repayment after one year",
        "",
        "   d) Current Liabilities:",
        "      - Creditors, accruals, bank overdraft, taxes payable, dividends payable",
        "      - Due for settlement within one year",
        "",
        "   e) Shareholders' Equity:",
        "      - Share capital (authorized, issued, paid-up)",
        "      - Reserves (general, specific, share premium)",
        "      - Retained earnings",
        "",
        "4. Preparation Steps for Company Balance Sheet:",
        "   a) Extract adjusted balances from trial balance and final accounts",
        "   b) Classify items as assets, liabilities, or equity",
        "   c) Further classify as fixed/current, non-current/current",
        "   d) Arrange in order of liquidity/permanence",
        "   e) Ensure accounting equation balances",
        "",
        "5. Analysis and Interpretation of Balance Sheet:",
        "   a) Liquidity Analysis:",
        "      - Current Ratio = Current Assets / Current Liabilities",
        "      - Quick Ratio = (Current Assets - Stock) / Current Liabilities",
        "",
        "   b) Solvency Analysis:",
        "      - Debt to Equity Ratio = Total Liabilities / Shareholders' Equity",
        "      - Indicates financial risk and capital structure",
        "",
        "   c) Efficiency Analysis:",
        "      - Asset Turnover = Sales / Total Assets",
        "      - Measures how efficiently assets generate revenue",
        "",
        "Nigerian Context:",
        "   - Nigerian companies prepare Balance Sheets in vertical format for NSE and SEC compliance",
        "   - CAMA 2020 requires detailed disclosure of assets, liabilities, and equity components",
        "   - Nigerian investors use Balance Sheet ratios to assess company financial health before investing",
        "   - Banks request Balance Sheets for loan assessment of Nigerian businesses",
        "",
        "Practical Activities:",
        "   - Teacher demonstrates preparation of company Balance Sheet with Nigerian corporate data",
        "   - Students practice classifying items and arranging in proper order",
        "   - Students calculate and interpret liquidity and solvency ratios from sample Balance Sheets",
        "",
        "Common Misconceptions:",
        "   - 'Balance Sheet shows profit': Balance Sheet shows financial position; Profit and Loss Account shows profit",
        "   - 'All assets are listed at market value': Assets are listed at historical cost less depreciation (except revalued assets)",
        "   - 'Higher current ratio is always better': Excessive current assets may indicate inefficient asset utilization",
        "",
        "Conclusion:",
        "   - Company Balance Sheet shows financial position at a specific date",
        "   - Items classified as fixed/current assets and non-current/current liabilities",
        "   - Ratio analysis helps interpret liquidity, solvency, and efficiency",
        "   - Mastery supports financial analysis, investment decisions, and regulatory compliance"
      ],
      "diagramDescriptions": [
        "Chart of company Balance Sheet format with vertical layout",
        "Diagram of asset and liability classification",
        "Sample ratio calculations for liquidity and solvency analysis",
        "Nigerian context: NSE-listed company Balance Sheet examples",
        "Common misconceptions and clarifications"
      ],
      "videoId": "",
      "youtubeQuery": "SS2 Financial Accounting company balance sheet preparation analysis interpretation site:youtube.com",
      "quiz": [
        {"q": "Company Balance Sheet is prepared to show:", "opts": ["Profit for the period", "Financial position at a date", "Cash flow", "Revenue sources"], "ans": 1, "explanation": "Balance Sheet shows the financial position (assets, liabilities, equity) at a specific date."},
        {"q": "In vertical Balance Sheet format, items are listed:", "opts": ["Assets on left, liabilities on right", "Assets first, then liabilities and equity below", "Liabilities first, then assets", "Random order"], "ans": 1, "explanation": "Vertical format lists assets first, followed by liabilities and shareholders' equity below."},
        {"q": "Fixed assets in Balance Sheet are shown at:", "opts": ["Original cost only", "Market value", "Net book value (cost less accumulated depreciation)", "Scrap value"], "ans": 2, "explanation": "Fixed assets are shown at net book value (cost less accumulated depreciation) in Balance Sheet."},
        {"q": "Current liabilities include:", "opts": ["Long-term loans", "Creditors, accruals, bank overdraft", "Share capital", "Retained earnings"], "ans": 1, "explanation": "Current liabilities are obligations due within one year like creditors, accruals, and bank overdraft."},
        {"q": "In Nigerian context, Balance Sheet preparation is essential for:", "opts": ["Only internal use", "NSE listing, SEC compliance, and bank loan applications", "Only marketing purposes", "Only employee records"], "ans": 1, "explanation": "Nigerian companies prepare Balance Sheets for NSE listing, SEC compliance, and bank loan assessments."},
        {"q": "Current Ratio is calculated as:", "opts": ["Current Assets + Current Liabilities", "Current Assets / Current Liabilities", "Current Liabilities / Current Assets", "Total Assets / Total Liabilities"], "ans": 1, "explanation": "Current Ratio = Current Assets ÷ Current Liabilities, measuring short-term liquidity."},
        {"q": "A common misconception about Balance Sheet is:", "opts": ["It shows financial position", "It is based on accounting equation", "It shows profit for the period", "It classifies assets and liabilities"], "ans": 2, "explanation": "Balance Sheet shows financial position at a date; Profit and Loss Account shows profit for a period."},
        {"q": "Shareholders' equity in Balance Sheet includes:", "opts": ["Only share capital", "Share capital, reserves, and retained earnings", "Only retained earnings", "Only reserves"], "ans": 1, "explanation": "Shareholders' equity includes share capital, reserves (general, specific, share premium), and retained earnings."},
        {"q": "To prepare company Balance Sheet, you need:", "opts": ["Only trial balance", "Adjusted trial balance with all final accounts", "Only cash book", "Only sales journal"], "ans": 1, "explanation": "Balance Sheet requires adjusted trial balance with all final accounts including appropriations and reserves."},
        {"q": "Debt to Equity Ratio measures:", "opts": ["Liquidity", "Solvency and financial risk", "Profitability", "Asset efficiency"], "ans": 1, "explanation": "Debt to Equity Ratio = Total Liabilities ÷ Shareholders' Equity, indicating financial risk and capital structure."}
      ]
    }
  ]
}